fastcan/_beam.py
fastcan/_cancorr_fast.cpython-39-darwin.so
fastcan/_fastcan.py
fastcan/_minibatch.py
fastcan/__init__.py
fastcan/_cancorr_fast.pyx
fastcan/meson.build
fastcan/_refine.py
fastcan/utils.py
fastcan/py.typed
fastcan/tests/test_utils.py
fastcan/tests/__init__.py
fastcan/tests/test_fastcan.py
fastcan/tests/test_minibatch.py
fastcan/tests/test_beam.py
fastcan/tests/test_refine.py
fastcan/tests/test_init.py
fastcan/narx/_base.py
fastcan/narx/_feature.py
fastcan/narx/__init__.py
fastcan/narx/meson.build
fastcan/narx/_narx_fast.pyx
fastcan/narx/_narx_fast.cpython-39-darwin.so
fastcan/narx/_utils.py
fastcan/narx/tests/test_narx.py
fastcan/narx/tests/__init__.py
fastcan/narx/tests/test_narx_jac.py
fastcan-0.5.0.dist-info/RECORD
fastcan-0.5.0.dist-info/LICENSE
fastcan-0.5.0.dist-info/WHEEL
fastcan-0.5.0.dist-info/METADATA
