Metadata-Version: 2.1
Name: fastcan
Version: 0.5.0
Summary: A fast canonical-correlation-based search algorithm
Author-Email: Matthew Sikai Zhang <matthew.szhang91@gmail.com>
License: MIT License
Classifier: Development Status :: 4 - Beta
Classifier: License :: OSI Approved :: MIT License
Classifier: Programming Language :: Python
Classifier: Operating System :: Microsoft :: Windows
Classifier: Operating System :: Unix
Classifier: Operating System :: MacOS
Classifier: Programming Language :: Python :: 3
Classifier: Programming Language :: Python :: 3.9
Classifier: Programming Language :: Python :: 3.10
Classifier: Programming Language :: Python :: 3.11
Classifier: Programming Language :: Python :: 3.12
Classifier: Programming Language :: Python :: 3.13
Classifier: Programming Language :: Python :: 3.14
Classifier: Programming Language :: Python :: Implementation :: CPython
Project-URL: homepage, https://fastcan.readthedocs.io/en/latest/
Project-URL: source, https://github.com/scikit-learn-contrib/fastcan
Project-URL: download, https://pypi.org/project/fastcan/#files
Project-URL: tracker, https://github.com/scikit-learn-contrib/fastcan/issues
Requires-Python: >=3.9
Requires-Dist: scikit-learn>=1.6.0
